{
    "metadata": {
        "generated_at": "2026-06-07T23:02:30.025Z",
        "tool": "JSON Generator Tool Arabic - Rata Kanan"
    },
    "konten": {
        "judul_utama": "Tawassul Dengan Nabi ﷺ",
        "pembuka_basmalah": "بِسْمِ اللّٰهِ الرَّحْمٰنِ الرَّحِيْمِ",
        "bait_list": [
            {
                "id": 1,
                "syathr_awal": "خَدَمْتُهُ بِمَدِيْحٍ أَسْتَقِيْلُ بِهِ",
                "syathr_tsani": "ذُنُوْبَ عُمْرٍ مَضَى فِى الشِّعْرِ وَالْخِدَمِ",
                "terjemahan": ""
            },
            {
                "id": 2,
                "syathr_awal": "اِذْ قَلَّدَانِيَ مَا تُخْشَى عَوَاقِبُهُ",
                "syathr_tsani": "كَأَ نَّنِيْ بِهِمَا هَدْيٌ مِنَ النَّعَمِ",
                "terjemahan": ""
            },
            {
                "id": 3,
                "syathr_awal": "أَطَعْتُ غَيَّ الصِّبَا فِى الْحَالَتَيْنِ وَمَا",
                "syathr_tsani": "حَصَلْتُ اِلَّا عَلَى الْآثَامِ وَالنَّدَمِ",
                "terjemahan": ""
            },
            {
                "id": 4,
                "syathr_awal": "فَيَا خَسَارَةَ نَفْسٍ فِيْ تِجَارَتِهَا",
                "syathr_tsani": "لَمْ تَشْتَرِ الدِّيْنَ بِالدُّنْيَا وَلَمْ تَسُمِ",
                "terjemahan": ""
            },
            {
                "id": 5,
                "syathr_awal": "وَمَنْ يَبِعْ آجِلًا مِنْهُ بِعَاجِلِهِ",
                "syathr_tsani": "يَبِنْ لَهُ الْغَبْنُ فِيْ بَيْعٍ وَفِيْ سَلَمِ",
                "terjemahan": ""
            },
            {
                "id": 6,
                "syathr_awal": "اِنْ آتِ ذَنْبًا فَمَا عَهْدِيْ بِمُنْتَقِضٍ",
                "syathr_tsani": "مِنَ النَّبِيِّ وَلَا حَبْلِيْ بِمُنْصَرِمِ",
                "terjemahan": ""
            },
            {
                "id": 7,
                "syathr_awal": "فَاِنَّ لِيْ ذِمَّةً مِنْهُ بِتَسْمِيَتِيْ",
                "syathr_tsani": "مُحَمَّدًا وَهْوَ أَوْفَى الْخَلْقِ بِالذِّمَمِ",
                "terjemahan": ""
            },
            {
                "id": 8,
                "syathr_awal": "اِنْ لَمْ يَكُنْ فِيْ مَعَادِيْ آخِذًا بِيَدِي",
                "syathr_tsani": "فَضْلًا وَاِلَّا فَقُلْ يَا زَلَّةَ الْقَدَمِ",
                "terjemahan": ""
            },
            {
                "id": 9,
                "syathr_awal": "حَاشَاهُ أَنْ يُحْرِمَ الرَّاجِيْ مَكَارِمَهُ",
                "syathr_tsani": "أَوْ يَرْجِعَ الْجَارُ مِنْهُ غَيْرَ مُحْتَرَمِ",
                "terjemahan": ""
            },
            {
                "id": 10,
                "syathr_awal": "وَمُنْذُ أَلْزَمْتُ أَفْكَارِيْ مَدَائِحَهُ",
                "syathr_tsani": "وَجَدْتُهُ لِخَلَاصِيْ خَيْرَ مُلْتَزِمِ",
                "terjemahan": ""
            },
            {
                "id": 11,
                "syathr_awal": "وَلَنْ يَفُوْتَ الْغِنَى مِنْهُ يَدًا تَرِبَتْ",
                "syathr_tsani": "اِنَّ الْحَيَا يُنْبِتُ الْأَزْهَارَ فِى الْأَ  كَمِ",
                "terjemahan": ""
            },
            {
                "id": 12,
                "syathr_awal": "وَلَمْ أُرِدْ زَهْرَةَ الدُّنْيَا الَّتِى اقْتَطَفَتْ",
                "syathr_tsani": "يَدَا زُهَيْرٍ بِمَا أَثْنَى عَلَى هَرِمِ",
                "terjemahan": ""
            }
        ]
    }
}
